fastcloudinit/__init__.py
fastcloudinit/_modidx.py
fastcloudinit/core.py
fastcloudinit-0.0.5.dist-info/licenses/LICENSE
fastcloudinit-0.0.5.dist-info/METADATA
fastcloudinit-0.0.5.dist-info/WHEEL
fastcloudinit-0.0.5.dist-info/entry_points.txt
fastcloudinit-0.0.5.dist-info/top_level.txt
fastcloudinit-0.0.5.dist-info/RECORD
